[
  {
    "id": "sub_dca5054a-446e-47a9-818c-258c4bc3ff4c",
    "formId": "employee-onboarding",
    "data": {
      "firstName": "John",
      "lastName": "Doe",
      "email": "john@example.com",
      "department": "engineering",
      "joinDate": "2025-12-15",
      "experience": 5,
      "skills": [
        "javascript",
        "typescript",
        "react"
      ],
      "bio": "Developer",
      "agreeToTerms": true
    },
    "createdAt": "2025-11-30T17:30:44.509Z",
    "updatedAt": "2025-11-30T17:30:44.509Z"
  },
  {
    "id": "sub_52744f71-638a-47f8-92e8-8895c1582476",
    "formId": "employee-onboarding",
    "data": {
      "firstName": "demo 2",
      "lastName": "demoooo",
      "email": "demo@mail.com",
      "department": "engineering",
      "joinDate": "2025-12-01",
      "experience": 2,
      "skills": [
        "javascript",
        "typescript"
      ],
      "bio": "nanananana",
      "agreeToTerms": true
    },
    "createdAt": "2025-12-01T14:57:06.068Z",
    "updatedAt": "2025-12-01T14:57:06.068Z"
  },
  {
    "id": "sub_17a2533c-2ea3-4e3d-88ee-ba77aaf859cb",
    "formId": "employee-onboarding",
    "data": {
      "firstName": "demo 3",
      "lastName": "demo 3",
      "email": "demoooo@gmail.com",
      "department": "product",
      "joinDate": "2025-12-01",
      "experience": 2,
      "skills": [
        "react"
      ],
      "bio": "nanananana",
      "agreeToTerms": false
    },
    "createdAt": "2025-12-01T15:06:01.599Z",
    "updatedAt": "2025-12-01T15:06:01.599Z"
  },
  {
    "id": "sub_e232183c-35ee-4f93-9924-ec10cc0cbc8c",
    "formId": "employee-onboarding",
    "data": {
      "firstName": "aaaaasssssdddddd",
      "lastName": "demoooo",
      "email": "abc@mail.com",
      "department": "engineering",
      "joinDate": "2025-12-01",
      "experience": 3,
      "skills": [
        "typescript",
        "react"
      ],
      "bio": "biurbiclsndkewnbxfesdfklcs",
      "agreeToTerms": false
    },
    "createdAt": "2025-12-01T15:12:15.378Z",
    "updatedAt": "2025-12-01T15:12:15.378Z"
  }
]